mtmpltool/__init__.py
mtmpltool/metric.py
mtmpltool/r2closs.py
mtmpltool/scheduler.py
mtmpltool/tee.py
mtmpltool/transform.py
mtmpltool/utils.py
mtmpltool/callbacks/__init__.py
mtmpltool/callbacks/rate_early_stopping.py
mtmpltool-0.0.6.dist-info/licenses/LICENSE
mtmpltool-0.0.6.dist-info/METADATA
mtmpltool-0.0.6.dist-info/WHEEL
mtmpltool-0.0.6.dist-info/top_level.txt
mtmpltool-0.0.6.dist-info/RECORD
