Metadata-Version: 2.4
Name: mtmpltool
Version: 0.0.6
Summary: Description
License: Apache License
Classifier: Development Status :: 3 - Alpha
Classifier: Programming Language :: Python :: 3.2
Classifier: Intended Audience :: Developers
Classifier: License :: OSI Approved :: MIT License
Classifier: Operating System :: MacOS
Classifier: Operating System :: POSIX :: Linux
Classifier: Operating System :: Microsoft :: Windows
Requires-Python: >=3.8
License-File: LICENSE
Requires-Dist: lightning
Requires-Dist: torch
Requires-Dist: pytorch-forecasting
Dynamic: license-file
